ambade_api_client/__init__.py
ambade_test-0.1.0.dist-info/METADATA
ambade_test-0.1.0.dist-info/WHEEL
ambade_test-0.1.0.dist-info/top_level.txt
ambade_test-0.1.0.dist-info/RECORD
