Metadata-Version: 2.4
Name: ambade-test
Version: 0.1.0
Summary: Client for Ambade embedding API
Author-email: ambade <ambade@email.com>
License-Expression: MIT
Requires-Python: >=3.8
Requires-Dist: requests
